pundesh/__init__.py
pundesh/pundesh.py
pundesh-0.0.4.dist-info/METADATA
pundesh-0.0.4.dist-info/WHEEL
pundesh-0.0.4.dist-info/top_level.txt
pundesh-0.0.4.dist-info/RECORD
