Metadata-Version: 2.4
Name: pundesh
Version: 0.0.4
Summary: Automation Toolkit: Google Maps Scraper and Electronics Bazaar Review Automation using Playwright
Author: Sidharth
Author-email: Sidharth <pundesh@email.com>
License: MIT
Keywords: google maps,scraper,web scraping,playwright,automation,reviews,colab
Classifier: Development Status :: 4 - Beta
Classifier: Intended Audience :: Developers
Classifier: License :: OSI Approved :: MIT License
Classifier: Programming Language :: Python :: 3
Classifier: Programming Language :: Python :: 3.8
Classifier: Programming Language :: Python :: 3.9
Classifier: Programming Language :: Python :: 3.10
Classifier: Programming Language :: Python :: 3.11
Classifier: Programming Language :: Python :: 3.12
Classifier: Topic :: Internet :: WWW/HTTP :: Browsers
Classifier: Topic :: Internet :: WWW/HTTP :: Indexing/Search
Requires-Python: >=3.8
Requires-Dist: playwright<2.0,>=1.40
Requires-Dist: pandas<3.0,>=1.5
Provides-Extra: stealth
Requires-Dist: playwright-stealth>=1.0.6; extra == "stealth"
Dynamic: author
Dynamic: requires-python
